README.rst
setup.py
bin/tessera-up
tessera_up/__init__.py
tessera_up.egg-info/PKG-INFO
tessera_up.egg-info/SOURCES.txt
tessera_up.egg-info/dependency_links.txt
tessera_up.egg-info/not-zip-safe
tessera_up.egg-info/requires.txt
tessera_up.egg-info/top_level.txt