Metadata-Version: 1.0
Name: tessera-up
Version: 0.0.2
Summary: Uploads dashboards to Tessera based on config directory
Home-page: UNKNOWN
Author: Nylas Team
Author-email: support@nylas.com
License: UNKNOWN
Platform: UNKNOWN
